{
  "context": {
    "date": "2025-06-24T13:37:05+00:00",
    "host_name": "chiatta01",
    "executable": "/home/ac.amillan/source/parallel-advection/build_dpcpp_pvc/benchmark/advection-bench",
    "num_cpus": 128,
    "mhz_per_cpu": 800,
    "cpu_scaling_enabled": false,
    "caches": [
      {
        "type": "Data",
        "level": 1,
        "size": 49152,
        "num_sharing": 2
      },
      {
        "type": "Instruction",
        "level": 1,
        "size": 32768,
        "num_sharing": 2
      },
      {
        "type": "Unified",
        "level": 2,
        "size": 2097152,
        "num_sharing": 2
      },
      {
        "type": "Unified",
        "level": 3,
        "size": 78643200,
        "num_sharing": 64
      }
    ],
    "load_avg": [0.605469,0.405762,0.168457],
    "library_build_type": "release"
  },
  "benchmarks": [
    {
      "name": "main-BKM-bench/1/0/0/512/1/1/real_time_mean",
      "family_index": 0,
      "per_family_instance_index": 0,
      "run_name": "main-BKM-bench/1/0/0/512/1/1/real_time",
      "run_type": "aggregate",
      "repetitions": 50,
      "threads": 1,
      "aggregate_name": "mean",
      "aggregate_unit": "time",
      "iterations": 50,
      "real_time": 9.5197248466094664e-01,
      "cpu_time": 9.5198123010899183e-01,
      "time_unit": "ms",
      "bytes_per_second": 5.6395942597236780e+11,
      "err": NaN,
      "gpu": 1.0000000000000000e+00,
      "items_per_second": 3.5247464123272987e+10,
      "kernel_id": 0.0000000000000000e+00,
      "n0": 3.2768000000000000e+04,
      "n1": 1.0240000000000000e+03,
      "n2": 1.0000000000000000e+00,
      "pref_wg_size": 5.1200000000000000e+02,
      "seq_size0": 1.0000000000000000e+00,
      "seq_size2": 1.0000000000000000e+00
    },
    {
      "name": "main-BKM-bench/1/0/0/512/1/1/real_time_median",
      "family_index": 0,
      "per_family_instance_index": 0,
      "run_name": "main-BKM-bench/1/0/0/512/1/1/real_time",
      "run_type": "aggregate",
      "repetitions": 50,
      "threads": 1,
      "aggregate_name": "median",
      "aggregate_unit": "time",
      "iterations": 50,
      "real_time": 9.5195274394670415e-01,
      "cpu_time": 9.5196608310626729e-01,
      "time_unit": "ms",
      "bytes_per_second": 5.6396802825969995e+11,
      "err": NaN,
      "gpu": 1.0000000000000000e+00,
      "items_per_second": 3.5248001766231247e+10,
      "kernel_id": 0.0000000000000000e+00,
      "n0": 3.2768000000000000e+04,
      "n1": 1.0240000000000000e+03,
      "n2": 1.0000000000000000e+00,
      "pref_wg_size": 5.1200000000000000e+02,
      "seq_size0": 1.0000000000000000e+00,
      "seq_size2": 1.0000000000000000e+00
    },
    {
      "name": "main-BKM-bench/1/0/0/512/1/1/real_time_stddev",
      "family_index": 0,
      "per_family_instance_index": 0,
      "run_name": "main-BKM-bench/1/0/0/512/1/1/real_time",
      "run_type": "aggregate",
      "repetitions": 50,
      "threads": 1,
      "aggregate_name": "stddev",
      "aggregate_unit": "time",
      "iterations": 50,
      "real_time": 2.2518357406825376e-03,
      "cpu_time": 2.2502293761178537e-03,
      "time_unit": "ms",
      "bytes_per_second": 1.3340625418707721e+09,
      "err": NaN,
      "gpu": 0.0000000000000000e+00,
      "items_per_second": 8.3378908866923258e+07,
      "kernel_id": 0.0000000000000000e+00,
      "n0": 0.0000000000000000e+00,
      "n1": 0.0000000000000000e+00,
      "n2": 0.0000000000000000e+00,
      "pref_wg_size": 0.0000000000000000e+00,
      "seq_size0": 0.0000000000000000e+00,
      "seq_size2": 0.0000000000000000e+00
    },
    {
      "name": "main-BKM-bench/1/0/0/512/1/1/real_time_cv",
      "family_index": 0,
      "per_family_instance_index": 0,
      "run_name": "main-BKM-bench/1/0/0/512/1/1/real_time",
      "run_type": "aggregate",
      "repetitions": 50,
      "threads": 1,
      "aggregate_name": "cv",
      "aggregate_unit": "percentage",
      "iterations": 50,
      "real_time": 2.3654420447714397e-03,
      "cpu_time": 2.3637329234529408e-03,
      "time_unit": "ms",
      "bytes_per_second": 2.3655292924142685e-03,
      "err": NaN,
      "gpu": 0.0000000000000000e+00,
      "items_per_second": 2.3655292924142685e-03,
      "kernel_id": NaN,
      "n0": 0.0000000000000000e+00,
      "n1": 0.0000000000000000e+00,
      "n2": 0.0000000000000000e+00,
      "pref_wg_size": 0.0000000000000000e+00,
      "seq_size0": 0.0000000000000000e+00,
      "seq_size2": 0.0000000000000000e+00
    },
    {
      "name": "main-BKM-bench/1/1/0/512/1/1/real_time_mean",
      "family_index": 0,
      "per_family_instance_index": 1,
      "run_name": "main-BKM-bench/1/1/0/512/1/1/real_time",
      "run_type": "aggregate",
      "repetitions": 50,
      "threads": 1,
      "aggregate_name": "mean",
      "aggregate_unit": "time",
      "iterations": 50,
      "real_time": 7.8641961942299143e-01,
      "cpu_time": 7.8640847163879568e-01,
      "time_unit": "ms",
      "bytes_per_second": 6.8269037773692920e+11,
      "err": NaN,
      "gpu": 1.0000000000000000e+00,
      "items_per_second": 4.2668148608558075e+10,
      "kernel_id": 1.0000000000000000e+00,
      "n0": 3.2768000000000000e+04,
      "n1": 1.0240000000000000e+03,
      "n2": 1.0000000000000000e+00,
      "pref_wg_size": 5.1200000000000000e+02,
      "seq_size0": 1.0000000000000000e+00,
      "seq_size2": 1.0000000000000000e+00
    },
    {
      "name": "main-BKM-bench/1/1/0/512/1/1/real_time_median",
      "family_index": 0,
      "per_family_instance_index": 1,
      "run_name": "main-BKM-bench/1/1/0/512/1/1/real_time",
      "run_type": "aggregate",
      "repetitions": 50,
      "threads": 1,
      "aggregate_name": "median",
      "aggregate_unit": "time",
      "iterations": 50,
      "real_time": 7.8571933555783258e-01,
      "cpu_time": 7.8572694314381020e-01,
      "time_unit": "ms",
      "bytes_per_second": 6.8328588739237793e+11,
      "err": NaN,
      "gpu": 1.0000000000000000e+00,
      "items_per_second": 4.2705367962023621e+10,
      "kernel_id": 1.0000000000000000e+00,
      "n0": 3.2768000000000000e+04,
      "n1": 1.0240000000000000e+03,
      "n2": 1.0000000000000000e+00,
      "pref_wg_size": 5.1200000000000000e+02,
      "seq_size0": 1.0000000000000000e+00,
      "seq_size2": 1.0000000000000000e+00
    },
    {
      "name": "main-BKM-bench/1/1/0/512/1/1/real_time_stddev",
      "family_index": 0,
      "per_family_instance_index": 1,
      "run_name": "main-BKM-bench/1/1/0/512/1/1/real_time",
      "run_type": "aggregate",
      "repetitions": 50,
      "threads": 1,
      "aggregate_name": "stddev",
      "aggregate_unit": "time",
      "iterations": 50,
      "real_time": 3.4631562174501072e-03,
      "cpu_time": 3.4409562962685338e-03,
      "time_unit": "ms",
      "bytes_per_second": 3.0039668576323700e+09,
      "err": NaN,
      "gpu": 0.0000000000000000e+00,
      "items_per_second": 1.8774792860202312e+08,
      "kernel_id": 0.0000000000000000e+00,
      "n0": 0.0000000000000000e+00,
      "n1": 0.0000000000000000e+00,
      "n2": 0.0000000000000000e+00,
      "pref_wg_size": 0.0000000000000000e+00,
      "seq_size0": 0.0000000000000000e+00,
      "seq_size2": 0.0000000000000000e+00
    },
    {
      "name": "main-BKM-bench/1/1/0/512/1/1/real_time_cv",
      "family_index": 0,
      "per_family_instance_index": 1,
      "run_name": "main-BKM-bench/1/1/0/512/1/1/real_time",
      "run_type": "aggregate",
      "repetitions": 50,
      "threads": 1,
      "aggregate_name": "cv",
      "aggregate_unit": "percentage",
      "iterations": 50,
      "real_time": 4.4037001772553432e-03,
      "cpu_time": 4.3755330980831475e-03,
      "time_unit": "ms",
      "bytes_per_second": 4.4001892447793241e-03,
      "err": NaN,
      "gpu": 0.0000000000000000e+00,
      "items_per_second": 4.4001892447793241e-03,
      "kernel_id": 0.0000000000000000e+00,
      "n0": 0.0000000000000000e+00,
      "n1": 0.0000000000000000e+00,
      "n2": 0.0000000000000000e+00,
      "pref_wg_size": 0.0000000000000000e+00,
      "seq_size0": 0.0000000000000000e+00,
      "seq_size2": 0.0000000000000000e+00
    },
    {
      "name": "main-BKM-bench/1/0/1/512/1/1/real_time_mean",
      "family_index": 0,
      "per_family_instance_index": 2,
      "run_name": "main-BKM-bench/1/0/1/512/1/1/real_time",
      "run_type": "aggregate",
      "repetitions": 50,
      "threads": 1,
      "aggregate_name": "mean",
      "aggregate_unit": "time",
      "iterations": 50,
      "real_time": 1.1386564733066524e+00,
      "cpu_time": 1.1385242684935886e+00,
      "time_unit": "ms",
      "bytes_per_second": 4.7149657428240448e+11,
      "err": NaN,
      "gpu": 1.0000000000000000e+00,
      "items_per_second": 2.9468535892650280e+10,
      "kernel_id": 0.0000000000000000e+00,
      "n0": 5.1200000000000000e+02,
      "n1": 1.0240000000000000e+03,
      "n2": 6.4000000000000000e+01,
      "pref_wg_size": 5.1200000000000000e+02,
      "seq_size0": 1.0000000000000000e+00,
      "seq_size2": 1.0000000000000000e+00
    },
    {
      "name": "main-BKM-bench/1/0/1/512/1/1/real_time_median",
      "family_index": 0,
      "per_family_instance_index": 2,
      "run_name": "main-BKM-bench/1/0/1/512/1/1/real_time",
      "run_type": "aggregate",
      "repetitions": 50,
      "threads": 1,
      "aggregate_name": "median",
      "aggregate_unit": "time",
      "iterations": 50,
      "real_time": 1.1388223499988015e+00,
      "cpu_time": 1.1386454006410143e+00,
      "time_unit": "ms",
      "bytes_per_second": 4.7142639283841663e+11,
      "err": NaN,
      "gpu": 1.0000000000000000e+00,
      "items_per_second": 2.9464149552401039e+10,
      "kernel_id": 0.0000000000000000e+00,
      "n0": 5.1200000000000000e+02,
      "n1": 1.0240000000000000e+03,
      "n2": 6.4000000000000000e+01,
      "pref_wg_size": 5.1200000000000000e+02,
      "seq_size0": 1.0000000000000000e+00,
      "seq_size2": 1.0000000000000000e+00
    },
    {
      "name": "main-BKM-bench/1/0/1/512/1/1/real_time_stddev",
      "family_index": 0,
      "per_family_instance_index": 2,
      "run_name": "main-BKM-bench/1/0/1/512/1/1/real_time",
      "run_type": "aggregate",
      "repetitions": 50,
      "threads": 1,
      "aggregate_name": "stddev",
      "aggregate_unit": "time",
      "iterations": 50,
      "real_time": 2.0527307390559497e-03,
      "cpu_time": 1.9906765774224400e-03,
      "time_unit": "ms",
      "bytes_per_second": 8.5225536717661691e+08,
      "err": NaN,
      "gpu": 0.0000000000000000e+00,
      "items_per_second": 5.3265960448538557e+07,
      "kernel_id": 0.0000000000000000e+00,
      "n0": 0.0000000000000000e+00,
      "n1": 0.0000000000000000e+00,
      "n2": 0.0000000000000000e+00,
      "pref_wg_size": 0.0000000000000000e+00,
      "seq_size0": 0.0000000000000000e+00,
      "seq_size2": 0.0000000000000000e+00
    },
    {
      "name": "main-BKM-bench/1/0/1/512/1/1/real_time_cv",
      "family_index": 0,
      "per_family_instance_index": 2,
      "run_name": "main-BKM-bench/1/0/1/512/1/1/real_time",
      "run_type": "aggregate",
      "repetitions": 50,
      "threads": 1,
      "aggregate_name": "cv",
      "aggregate_unit": "percentage",
      "iterations": 50,
      "real_time": 1.8027656164767852e-03,
      "cpu_time": 1.7484709219737200e-03,
      "time_unit": "ms",
      "bytes_per_second": 1.8075536783564319e-03,
      "err": NaN,
      "gpu": 0.0000000000000000e+00,
      "items_per_second": 1.8075536783564319e-03,
      "kernel_id": NaN,
      "n0": 0.0000000000000000e+00,
      "n1": 0.0000000000000000e+00,
      "n2": 0.0000000000000000e+00,
      "pref_wg_size": 0.0000000000000000e+00,
      "seq_size0": 0.0000000000000000e+00,
      "seq_size2": 0.0000000000000000e+00
    },
    {
      "name": "main-BKM-bench/1/1/1/512/1/1/real_time_mean",
      "family_index": 0,
      "per_family_instance_index": 3,
      "run_name": "main-BKM-bench/1/1/1/512/1/1/real_time",
      "run_type": "aggregate",
      "repetitions": 50,
      "threads": 1,
      "aggregate_name": "mean",
      "aggregate_unit": "time",
      "iterations": 50,
      "real_time": 2.0050753152296803e+00,
      "cpu_time": 2.0050839075071631e+00,
      "time_unit": "ms",
      "bytes_per_second": 2.6775598360529935e+11,
      "err": NaN,
      "gpu": 1.0000000000000000e+00,
      "items_per_second": 1.6734748975331209e+10,
      "kernel_id": 1.0000000000000000e+00,
      "n0": 5.1200000000000000e+02,
      "n1": 1.0240000000000000e+03,
      "n2": 6.4000000000000000e+01,
      "pref_wg_size": 5.1200000000000000e+02,
      "seq_size0": 1.0000000000000000e+00,
      "seq_size2": 1.0000000000000000e+00
    },
    {
      "name": "main-BKM-bench/1/1/1/512/1/1/real_time_median",
      "family_index": 0,
      "per_family_instance_index": 3,
      "run_name": "main-BKM-bench/1/1/1/512/1/1/real_time",
      "run_type": "aggregate",
      "repetitions": 50,
      "threads": 1,
      "aggregate_name": "median",
      "aggregate_unit": "time",
      "iterations": 50,
      "real_time": 2.0050871873776130e+00,
      "cpu_time": 2.0050991819484105e+00,
      "time_unit": "ms",
      "bytes_per_second": 2.6775439760416016e+11,
      "err": NaN,
      "gpu": 1.0000000000000000e+00,
      "items_per_second": 1.6734649850260010e+10,
      "kernel_id": 1.0000000000000000e+00,
      "n0": 5.1200000000000000e+02,
      "n1": 1.0240000000000000e+03,
      "n2": 6.4000000000000000e+01,
      "pref_wg_size": 5.1200000000000000e+02,
      "seq_size0": 1.0000000000000000e+00,
      "seq_size2": 1.0000000000000000e+00
    },
    {
      "name": "main-BKM-bench/1/1/1/512/1/1/real_time_stddev",
      "family_index": 0,
      "per_family_instance_index": 3,
      "run_name": "main-BKM-bench/1/1/1/512/1/1/real_time",
      "run_type": "aggregate",
      "repetitions": 50,
      "threads": 1,
      "aggregate_name": "stddev",
      "aggregate_unit": "time",
      "iterations": 50,
      "real_time": 9.7025239597931908e-05,
      "cpu_time": 1.0093248445893315e-04,
      "time_unit": "ms",
      "bytes_per_second": 1.2957164139821867e+07,
      "err": NaN,
      "gpu": 0.0000000000000000e+00,
      "items_per_second": 8.0982275873886666e+05,
      "kernel_id": 0.0000000000000000e+00,
      "n0": 0.0000000000000000e+00,
      "n1": 0.0000000000000000e+00,
      "n2": 0.0000000000000000e+00,
      "pref_wg_size": 0.0000000000000000e+00,
      "seq_size0": 0.0000000000000000e+00,
      "seq_size2": 0.0000000000000000e+00
    },
    {
      "name": "main-BKM-bench/1/1/1/512/1/1/real_time_cv",
      "family_index": 0,
      "per_family_instance_index": 3,
      "run_name": "main-BKM-bench/1/1/1/512/1/1/real_time",
      "run_type": "aggregate",
      "repetitions": 50,
      "threads": 1,
      "aggregate_name": "cv",
      "aggregate_unit": "percentage",
      "iterations": 50,
      "real_time": 4.8389822996158989e-05,
      "cpu_time": 5.0338284637882449e-05,
      "time_unit": "ms",
      "bytes_per_second": 4.8391688452132215e-05,
      "err": NaN,
      "gpu": 0.0000000000000000e+00,
      "items_per_second": 4.8391688452132215e-05,
      "kernel_id": 0.0000000000000000e+00,
      "n0": 0.0000000000000000e+00,
      "n1": 0.0000000000000000e+00,
      "n2": 0.0000000000000000e+00,
      "pref_wg_size": 0.0000000000000000e+00,
      "seq_size0": 0.0000000000000000e+00,
      "seq_size2": 0.0000000000000000e+00
    }
  ]
}
